fsoopify/__init__.py
fsoopify/atomic.py
fsoopify/hashs.py
fsoopify/nodes.py
fsoopify/openers.py
fsoopify/paths.py
fsoopify/serialize.py
fsoopify/serialize_ctx.py
fsoopify/size.py
fsoopify/tree.py
fsoopify/utils.py
fsoopify-0.5.2.dist-info/LICENSE
fsoopify-0.5.2.dist-info/METADATA
fsoopify-0.5.2.dist-info/WHEEL
fsoopify-0.5.2.dist-info/top_level.txt
fsoopify-0.5.2.dist-info/RECORD
