Metadata-Version: 2.1
Name: fsoopify
Version: 0.5.2
Summary: UNKNOWN
Home-page: https://github.com/Cologler/fsoopify-python
Author: Cologler
Author-email: skyoflw@gmail.com
License: MIT License
Keywords: python,fs,oop,oopify,filesystem
Platform: UNKNOWN
Classifier: Development Status :: 5 - Production/Stable
Classifier: License :: OSI Approved :: MIT License
Classifier: Programming Language :: Python :: 3.6
Classifier: Programming Language :: Python :: 3.7
Classifier: Programming Language :: Python :: 3.8
Requires-Dist: anyser (<0.2.0,>=0.1.1)
Requires-Dist: atomicwrites (<2.0.0,>=1.4.0)
Requires-Dist: filelock (<4.0.0,>=3.0.12)
Requires-Dist: portalocker (<3.0.0,>=2.0.0)
